django_admin_dracula/__init__.py
django_admin_dracula/static/admin/css/base.css
django_admin_dracula/static/admin/css/changelists.css
django_admin_dracula/static/admin/css/dark_mode.css
django_admin_dracula/static/admin/css/forms.css
django_admin_dracula/static/admin/css/nav_sidebar.css
django_admin_dracula/static/admin/css/widgets.css
django_admin_dracula/static/admin/img/calendar-icons.svg
django_admin_dracula/static/admin/img/icon-addlink.svg
django_admin_dracula/static/admin/img/icon-calendar.svg
django_admin_dracula/static/admin/img/icon-changelink.svg
django_admin_dracula/static/admin/img/icon-clock.svg
django_admin_dracula/static/admin/img/icon-hidelink.svg
django_admin_dracula/static/admin/img/icon-no.svg
django_admin_dracula/static/admin/img/icon-unknown.svg
django_admin_dracula/static/admin/img/icon-viewlink.svg
django_admin_dracula/static/admin/img/icon-yes.svg
django_admin_dracula/static/admin/img/search.svg
django_admin_dracula/static/admin/img/selector-icons.svg
django_admin_dracula/templates/admin/base.html
django_admin_dracula/templates/admin/base_site.html
django_admin_dracula/templates/admin/change_form.html
django_admin_dracula/templates/admin/change_list.html
django_admin_dracula/templates/admin/color_theme_toggle.html
django_admin_dracula-0.0.2.dist-info/METADATA
django_admin_dracula-0.0.2.dist-info/WHEEL
django_admin_dracula-0.0.2.dist-info/licenses/LICENSE
django_admin_dracula-0.0.2.dist-info/RECORD
