Metadata-Version: 2.3
Name: django-admin-dracula
Version: 0.0.2
Summary: Dracula theme for the Django admin
Project-URL: Homepage, https://github.com/sjbitcode/django-admin-dracula
Project-URL: Repository, https://github.com/sjbitcode/django-admin-dracula
Project-URL: Issues, https://github.com/sjbitcode/django-admin-dracula/issues
Author-email: Sangeeta Jadoonanan <sjbitcode@gmail.com>
License-Expression: MIT
License-File: LICENSE
Keywords: django,django admin,dracula,dracula theme,python
Classifier: Environment :: Web Environment
Classifier: Framework :: Django
Classifier: Framework :: Django :: 4.2
Classifier: Framework :: Django :: 5.0
Classifier: Framework :: Django :: 5.1
Classifier: Intended Audience :: Developers
Classifier: License :: OSI Approved :: MIT License
Classifier: Programming Language :: Python :: 3
Classifier: Programming Language :: Python :: 3.9
Classifier: Programming Language :: Python :: 3.10
Classifier: Programming Language :: Python :: 3.11
Classifier: Programming Language :: Python :: 3.12
Classifier: Programming Language :: Python :: 3.13
Requires-Python: >=3.9
Requires-Dist: django>=4.2
